_qepler.cp39-win32.pyd
feyn/CHANGELOG.md
feyn/VERSION
feyn/__init__.py
feyn/_base_reporting_mixin.py
feyn/_checklicense.py
feyn/_compatibility.py
feyn/_functions.py
feyn/_interactivemixin.py
feyn/_model.py
feyn/_plots_mixin.py
feyn/_program.py
feyn/_ql_notebook_mixin.py
feyn/_qlattice.py
feyn/_selection.py
feyn/_svgrenderer.py
feyn/_trainer.py
feyn/_typings.py
feyn/_validation.py
feyn/_version.py
feyn/_basealgo/__init__.py
feyn/_basealgo/_basealgo.py
feyn/_basealgo/_pmf.py
feyn/_basealgo/_programcollection.py
feyn/_criteria/__init__.py
feyn/_criteria/_bootstrap.py
feyn/_criteria/_clustering.py
feyn/_criteria/_readability.py
feyn/_criteria/_structural.py
feyn/_logging/__init__.py
feyn/_logging/_jupyter_logger.py
feyn/_logging/_logging.py
feyn/_qepler/__init__.py
feyn/_qepler/qeplertrainer.py
feyn/_query/__init__.py
feyn/_query/_query.py
feyn/_query/query_grammar.lark
feyn/datasets/__init__.py
feyn/datasets/_synthetic.py
feyn/filters/__init__.py
feyn/inference/__init__.py
feyn/inference/_TMLE/__init__.py
feyn/inference/_TMLE/_glm_bernoulli.py
feyn/inference/_TMLE/_tmle.py
feyn/insights/__init__.py
feyn/insights/_importance_table.py
feyn/insights/_shap/__init__.py
feyn/insights/_shap/_explainermodel.py
feyn/insights/_shap/_kernelshap.py
feyn/losses/__init__.py
feyn/losses/_lossfunctions.py
feyn/metrics/__init__.py
feyn/metrics/_contribution.py
feyn/metrics/_diversity.py
feyn/metrics/_linear.py
feyn/metrics/_metrics.py
feyn/metrics/_mutual.py
feyn/metrics/_normalization.py
feyn/metrics/_posterior.py
feyn/metrics/_pvalues.py
feyn/metrics/_spearman.py
feyn/metrics/_xi.py
feyn/plots/__init__.py
feyn/plots/_auto.py
feyn/plots/_graph_flow.py
feyn/plots/_model_response.py
feyn/plots/_model_response_2d.py
feyn/plots/_model_summary.py
feyn/plots/_plots.py
feyn/plots/_pr_curve.py
feyn/plots/_probability_plot.py
feyn/plots/_roc_curve.py
feyn/plots/_set_style.py
feyn/plots/_svg_toolkit.py
feyn/plots/_table_writer.py
feyn/plots/_themes.py
feyn/plots/_mpl/__init__.py
feyn-3.5.0.dist-info/LICENSE
feyn-3.5.0.dist-info/METADATA
feyn-3.5.0.dist-info/WHEEL
feyn-3.5.0.dist-info/top_level.txt
feyn-3.5.0.dist-info/RECORD
