Metadata-Version: 2.1
Name: feyn
Version: 3.5.0
Summary: Feyn is a symbolic regression package named after Richard Feynman, that uses the QLattice as a simulator to generate models.
Author-email: Abzu <support@abzu.ai>
License: CC-BY-NC-ND-4.0
Project-URL: Homepage, https://abzu.ai
Project-URL: Documentation, https://docs.abzu.ai
Classifier: Development Status :: 5 - Production/Stable
Classifier: Environment :: Console
Classifier: Environment :: Web Environment
Classifier: Intended Audience :: Science/Research
Classifier: Intended Audience :: Developers
Classifier: Operating System :: POSIX :: Linux
Classifier: Operating System :: MacOS
Classifier: Operating System :: Microsoft :: Windows
Classifier: Programming Language :: C
Classifier: Programming Language :: Python :: 3
Classifier: Topic :: Scientific/Engineering :: Artificial Intelligence
Classifier: Topic :: Software Development
Requires-Python: >=3.8
License-File: LICENSE
Requires-Dist: numpy >=1.24
Requires-Dist: pynacl
Requires-Dist: pandas
Requires-Dist: lark
Requires-Dist: svgwrite
Requires-Dist: matplotlib >=3.7.0
Requires-Dist: scikit-learn
Requires-Dist: sympy
Provides-Extra: extras
Requires-Dist: ipython ; extra == 'extras'
Requires-Dist: ipywidgets ; extra == 'extras'
Provides-Extra: tests
Requires-Dist: statsmodels ; extra == 'tests'
Requires-Dist: pytest ; extra == 'tests'
Requires-Dist: ipykernel ; extra == 'tests'
Requires-Dist: pyarrow ==17.0.0 ; (python_version < "3.13") and extra == 'tests'
Requires-Dist: pyarrow ==18.0.0 ; (python_version == "3.13") and extra == 'tests'
